youtube_clippy-1.0.1.dist-info/licenses/LICENSE
ytclip/__init__.py
ytclip/__main__.py
ytclip/cli.py
youtube_clippy-1.0.1.dist-info/METADATA
youtube_clippy-1.0.1.dist-info/WHEEL
youtube_clippy-1.0.1.dist-info/entry_points.txt
youtube_clippy-1.0.1.dist-info/top_level.txt
youtube_clippy-1.0.1.dist-info/RECORD
