Metadata-Version: 2.4
Name: youtube-clippy
Version: 1.0.1
Summary: A fast YouTube video clip downloader with timestamp support
Home-page: https://github.com/yourusername/ytclip
Author: Your Name
Author-email: Your Name <your.email@example.com>
License: MIT
Project-URL: Homepage, https://github.com/yourusername/ytclip
Project-URL: Issues, https://github.com/yourusername/ytclip/issues
Keywords: youtube,video,downloader,clip,timestamp,ffmpeg
Classifier: Development Status :: 4 - Beta
Classifier: Intended Audience :: End Users/Desktop
Classifier: Topic :: Multimedia :: Video
Classifier: License :: OSI Approved :: MIT License
Classifier: Programming Language :: Python :: 3
Classifier: Programming Language :: Python :: 3.7
Classifier: Programming Language :: Python :: 3.8
Classifier: Programming Language :: Python :: 3.9
Classifier: Programming Language :: Python :: 3.10
Classifier: Programming Language :: Python :: 3.11
Classifier: Operating System :: OS Independent
Requires-Python: >=3.7
License-File: LICENSE
Requires-Dist: yt-dlp>=2024.1.0
Dynamic: author
Dynamic: home-page
Dynamic: license-file
Dynamic: requires-python
